chora_mcp_manifest/__init__.py
chora_mcp_manifest/main.py
chora_mcp_manifest/models.py
chora_mcp_manifest/registry.py
chora_mcp_manifest/server.py
chora_mcp_manifest/tools.py
chora_mcp_manifest-0.1.0.dist-info/entry_points.txt
chora_mcp_manifest-0.1.0.dist-info/METADATA
chora_mcp_manifest-0.1.0.dist-info/WHEEL
chora_mcp_manifest-0.1.0.dist-info/RECORD
