Metadata-Version: 2.4
Name: chora-mcp-manifest
Version: 0.1.0
Summary: Registry management server for MCP ecosystem
License: MIT
Keywords: mcp,registry,manifest,discovery
Author: Liminal Commons
Author-email: team@liminalcommons.org
Requires-Python: >=3.11,<4.0
Classifier: License :: OSI Approved :: MIT License
Classifier: Programming Language :: Python :: 3
Classifier: Programming Language :: Python :: 3.11
Classifier: Programming Language :: Python :: 3.12
Classifier: Programming Language :: Python :: 3.13
Classifier: Programming Language :: Python :: 3.14
Requires-Dist: fastapi (>=0.109.0,<0.110.0)
Requires-Dist: httpx (>=0.26.0,<0.27.0)
Requires-Dist: pydantic (>=2.5.0,<3.0.0)
Requires-Dist: uvicorn (>=0.27.0,<0.28.0)
Project-URL: Bug Tracker, https://github.com/liminalcommons/chora-mcp-manifest/issues
Project-URL: Homepage, https://github.com/liminalcommons/chora-mcp-manifest
Project-URL: Repository, https://github.com/liminalcommons/chora-mcp-manifest
